{
  "plants": [
    {
      "id": "apple_granny_smith",
      "speciesId": "apple",
      "cultivarId": "granny_smith"
    },
    {
      "id": "apple_fuji",
      "speciesId": "apple",
      "cultivarId": "fuji"
    },
    {
      "id": "banana_cavendish",
      "speciesId": "banana",
      "cultivarId": "cavendish"
    },
    {
      "id": "haskap",
      "speciesId": "haskap",
      "cultivarId": null
    },
    {
      "id": "comfrey",
      "speciesId": "comfrey",
      "cultivarId": null
    },
    {
      "id": "28e38d4b-9813-4a06-866a-37e00fa82c8d",
      "speciesId": "nashi_pear",
      "cultivarId": "__unknown_cultivar__"
    },
    {
      "id": "40a22e74-9e9e-4ec6-a498-ed3acff4a011",
      "speciesId": "nanking_cherry",
      "cultivarId": "__unknown_cultivar__"
    },
    {
      "id": "b55eb666-3f93-4f1f-891e-e2a2b4034f15",
      "speciesId": "sweet_william",
      "cultivarId": null
    },
    {
      "id": "290e85d9-fdda-4afb-a673-07bad480381e",
      "speciesId": "carpathian_bellflower",
      "cultivarId": null
    },
    {
      "id": "86d0ca47-d661-4117-a2a6-3a2f2723fd43",
      "speciesId": "plantago_major",
      "cultivarId": null
    },
    {
      "id": "333ca36a-0dd1-4078-ab2f-1373902682c7",
      "speciesId": "pear",
      "cultivarId": "morettini"
    },
    {
      "id": "7362c53a-541b-439d-b5ad-fe97ed89c3a1",
      "speciesId": "strawberry",
      "cultivarId": null
    },
    {
      "id": "50f3c3b2-8245-48b8-9232-b1bac25102f5",
      "speciesId": "chives",
      "cultivarId": "common"
    },
    {
      "id": "f1a6ffb3-885c-4616-a85d-96ed9edcb20d",
      "speciesId": "calendula",
      "cultivarId": null
    },
    {
      "id": "97bb8174-9504-4555-bd15-d0a00baaa4d3",
      "speciesId": "fig",
      "cultivarId": "brown_turkey"
    },
    {
      "id": "26e224c9-7899-4fd1-b430-a4cbeacd1e6a",
      "speciesId": "nasturtium",
      "cultivarId": null
    },
    {
      "id": "e4b943a1-a9dc-4d5b-9519-866ce76c7b5b",
      "speciesId": "plantain",
      "cultivarId": "ribwort"
    },
    {
      "id": "25abbbc7-8bcd-49d5-982f-66894e95db79",
      "speciesId": "persimmon",
      "cultivarId": null
    },
    {
      "id": "063f1d51-510d-4013-a936-f86b69133aac",
      "speciesId": "yamlina",
      "cultivarId": null
    },
    {
      "id": "d4bc4262-5b2a-451f-8cf4-707cc2e6748d",
      "speciesId": "gooseberry",
      "cultivarId": null
    },
    {
      "id": "aaf9778b-c7aa-4442-8df4-04f7214271b9",
      "speciesId": "dill",
      "cultivarId": null
    },
    {
      "id": "fe606b96-7777-42ab-9dde-7e7e59f489ba",
      "speciesId": "livingstone_daisy",
      "cultivarId": null
    },
    {
      "id": "957fcea9-301b-43df-ae84-61b42260c88e",
      "speciesId": "apple",
      "cultivarId": "apistar"
    },
    {
      "id": "f832d85c-f9f8-419c-89fc-99eed038f996",
      "speciesId": "thyme",
      "cultivarId": "creeping"
    },
    {
      "id": "049cebd6-387a-4c22-bb42-af9d7a0838a3",
      "speciesId": "sour_cherry",
      "cultivarId": null
    },
    {
      "id": "027ef50a-61db-4c08-b5f3-2a34fd2fa979",
      "speciesId": "curry_plant",
      "cultivarId": null
    },
    {
      "id": "d20040cf-69af-4f3b-a992-5ec8ed1fea2c",
      "speciesId": "rosehip",
      "cultivarId": "ornamental"
    },
    {
      "id": "4d085563-c2cf-465c-b422-48fd2b5a5773",
      "speciesId": "che",
      "cultivarId": "seedless"
    },
    {
      "id": "fa1fbb36-f6fd-4880-9c6b-2e4c9ecdde74",
      "speciesId": "black_currant",
      "cultivarId": null
    },
    {
      "id": "f6da31c7-4545-4ef5-962f-ef55a7c54c0c",
      "speciesId": "red_currant",
      "cultivarId": null
    },
    {
      "id": "73602481-4f18-41a2-94bd-71eb89ab5933",
      "speciesId": "daisy",
      "cultivarId": null
    }
  ]
}